gcp_microservice_management/__init__.py
gcp_microservice_management/constants.py
gcp_microservice_management/deploy_app_sdk.py
gcp_microservice_management/deploy_to_cloud_run.py
gcp_microservice_management/docker_util.py
gcp_microservice_management/env_util.py
gcp_microservice_management/google_api_util.py
gcp_microservice_management/util.py
gcp_microservice_management-0.8.8.dist-info/LICENSE
gcp_microservice_management-0.8.8.dist-info/METADATA
gcp_microservice_management-0.8.8.dist-info/WHEEL
gcp_microservice_management-0.8.8.dist-info/RECORD
